{"SubTexture":[{"frameWidth":219,"y":369,"frameHeight":100,"width":214,"frameX":0,"height":90,"name":"glow_7","frameY":-6,"x":1},{"frameWidth":219,"y":461,"frameHeight":100,"width":214,"frameX":0,"height":90,"name":"glow_6","frameY":-6,"x":1},{"frameWidth":219,"y":185,"frameHeight":100,"width":215,"frameX":0,"height":90,"name":"glow_10","frameY":-6,"x":1},{"frameWidth":219,"y":461,"frameHeight":100,"width":214,"frameX":0,"height":90,"name":"glow_8","frameY":-6,"x":217},{"frameWidth":219,"y":1,"frameHeight":100,"width":215,"frameX":0,"height":90,"name":"glow_0","frameY":-6,"x":1},{"frameWidth":219,"y":93,"frameHeight":100,"width":215,"frameX":0,"height":90,"name":"glow_4","frameY":-6,"x":218},{"frameWidth":219,"y":277,"frameHeight":100,"width":215,"frameX":0,"height":90,"name":"glow_9","frameY":-6,"x":1},{"frameWidth":219,"y":369,"frameHeight":100,"width":214,"frameX":0,"height":90,"name":"glow_5","frameY":-6,"x":217},{"frameWidth":219,"y":185,"frameHeight":100,"width":215,"frameX":0,"height":90,"name":"glow_2","frameY":-6,"x":218},{"frameWidth":219,"y":93,"frameHeight":100,"width":215,"frameX":0,"height":90,"name":"glow_1","frameY":-6,"x":1},{"frameWidth":219,"y":277,"frameHeight":100,"width":215,"frameX":0,"height":90,"name":"glow_11","frameY":-6,"x":218},{"frameWidth":219,"y":1,"frameHeight":100,"width":215,"frameX":0,"height":90,"name":"glow_3","frameY":-6,"x":218}],"width":512,"height":1024,"name":"slwh_effect_starTrailing","imagePath":"slwh_effect_starTrailing_tex.png"}