{"frameRate":24,"name":"bar_effect_banker","version":"5.5","compatibleVersion":"5.5","armature":[{"type":"Armature","frameRate":24,"name":"bar_effect_banker","aabb":{"x":-57,"y":-57,"width":114,"height":114},"bone":[{"name":"root"},{"name":"banker","parent":"root"},{"name":"banker1","parent":"root"},{"name":"banker11","parent":"root"}],"slot":[{"name":"bank","parent":"banker"},{"blendMode":"add","name":"bank1","parent":"banker1"},{"blendMode":"add","name":"bank11","parent":"banker11"}],"skin":[{"slot":[{"name":"bank11","display":[{"name":"bar_random_banker"}]},{"name":"bank","display":[{"name":"bar_random_banker"}]},{"name":"bank1","display":[{"name":"bar_random_banker"}]}]}],"animation":[{"duration":27,"playTimes":0,"name":"newAnimation","bone":[{"name":"banker","scaleFrame":[{"duration":4,"curve":[0,0,0.5,1],"x":3,"y":3},{"duration":23}]},{"name":"banker1","scaleFrame":[{"duration":4,"curve":[0,0,0.5,1],"x":3,"y":3},{"duration":14,"curve":[0,0,0.5,1]},{"duration":9,"x":1.5,"y":1.5}]},{"name":"banker11","scaleFrame":[{"duration":10,"curve":[0,0,0.5,1],"x":3,"y":3},{"duration":17,"curve":[0,0,0.5,1]},{"duration":0,"x":1.5,"y":1.5}]}],"slot":[{"name":"bank","colorFrame":[{"duration":4,"tweenEasing":0,"value":{"aM":0}},{"duration":23}]},{"name":"bank1","colorFrame":[{"duration":3,"tweenEasing":0,"value":{"aM":0}},{"tweenEasing":0,"value":{"aM":0}},{"duration":14,"tweenEasing":0},{"duration":9,"value":{"aM":0}}]},{"name":"bank11","colorFrame":[{"duration":9,"tweenEasing":0,"value":{"aM":0}},{"tweenEasing":0,"value":{"aM":0}},{"duration":17,"tweenEasing":0},{"duration":0,"value":{"aM":0}}]}]}],"defaultActions":[{"gotoAndPlay":"newAnimation"}]}]}