{"width":512,"imagePath":"kpqznn_effect_hall_6_tex.png","height":512,"name":"kpqznn_effect_hall_6","SubTexture":[{"width":139,"y":1,"height":112,"name":"皇冠","x":1},{"width":161,"y":1,"height":62,"name":"金币","x":142},{"y":325,"frameX":-12,"frameHeight":64,"frameY":-2,"width":48,"frameWidth":64,"height":54,"name":"星光_00000","x":1},{"y":325,"frameX":-2,"frameHeight":32,"frameY":-3,"width":16,"frameWidth":20,"height":27,"name":"宝石","x":51},{"y":115,"frameX":0,"frameHeight":112,"frameY":-21,"width":139,"frameWidth":139,"height":68,"name":"xulie_00010","x":1},{"y":65,"frameX":0,"frameHeight":112,"frameY":-21,"width":139,"frameWidth":139,"height":68,"name":"xulie_00000","x":142},{"y":185,"frameX":0,"frameHeight":112,"frameY":-21,"width":139,"frameWidth":139,"height":68,"name":"xulie_00006","x":1},{"y":275,"frameX":0,"frameHeight":112,"frameY":-21,"width":139,"frameWidth":139,"height":68,"name":"xulie_00004","x":142},{"y":141,"frameX":0,"frameHeight":112,"frameY":-21,"width":139,"frameWidth":139,"height":68,"name":"xulie_00003","x":283},{"y":255,"frameX":0,"frameHeight":112,"frameY":-21,"width":139,"frameWidth":139,"height":68,"name":"xulie_00001","x":1},{"y":135,"frameX":0,"frameHeight":112,"frameY":-21,"width":139,"frameWidth":139,"height":68,"name":"xulie_00008","x":142},{"y":211,"frameX":0,"frameHeight":112,"frameY":-21,"width":139,"frameWidth":139,"height":68,"name":"xulie_00009","x":283},{"y":71,"frameX":0,"frameHeight":112,"frameY":-21,"width":139,"frameWidth":139,"height":68,"name":"xulie_00005","x":283},{"y":205,"frameX":0,"frameHeight":112,"frameY":-21,"width":139,"frameWidth":139,"height":68,"name":"xulie_00002","x":142},{"y":1,"frameX":0,"frameHeight":112,"frameY":-21,"width":139,"frameWidth":139,"height":68,"name":"xulie_00007","x":305}]}